[{"caption":"Table 1: Size of sentences, tokens, and labels for training, validation and test sets. \nPOS \nCoNLL2000 CoNLL2003 \ntraining \nsentence # \n39831 \n8936 \n14987 \ntoken # \n950011 \n211727 \n204567 \nvalidation sentence # \n1699 \nN/A \n3466 \ntoken # \n40068 \nN/A \n51578 \ntest \nsentences # \n2415 \n2012 \n3684 \ntoken # \n56671 \n47377 \n46666 \nlabel # \n45 \n22 \n9 \n\n4.3 Results \n\nWe train LSTM, BI-LSTM, CRF, LSTM-CRF and \nBI-LSTM-CRF models for each data set. We \nhave two ways to initialize word embedding: Ran-\ndom and Senna. We randomly initialize the word \nembedding vectors in the first category, and use \nSenna word embedding in the second category. \nFor each category, we use identical feature sets, \nthus different results are solely due to different \nnetworks. We train models using training data \nand monitor performance on validation data. As \nchunking data do not have a validation data set, \nwe use part of training data for validation purpose. \n","rows":["sentence #","N / A","training","token #","8936"],"columns":["N / A","test","3684","CoNLL2000","2012","CoNLL2003","token #","label #","204567","2415","211727","1699","Table 1 : Size of sentences , tokens , and labels for training , validation and test sets .","POS","3466","950011","validation"],"mergedAllColumns":[],"numberCells":[{"number":"56671","isBolded":false,"associatedRows":["token #"],"associatedColumns":["Table 1 : Size of sentences , tokens , and labels for training , validation and test sets .","POS","950011","1699","2415"],"associatedMergedColumns":[]},{"number":"39831","isBolded":false,"associatedRows":["training","sentence #"],"associatedColumns":["Table 1 : Size of sentences , tokens , and labels for training , validation and test sets .","POS"],"associatedMergedColumns":[]},{"number":"47377","isBolded":false,"associatedRows":["token #"],"associatedColumns":["Table 1 : Size of sentences , tokens , and labels for training , validation and test sets .","CoNLL2000","211727","N / A","2012"],"associatedMergedColumns":[]},{"number":"4.3","isBolded":true,"associatedRows":[],"associatedColumns":["Table 1 : Size of sentences , tokens , and labels for training , validation and test sets .","POS","token #","validation","test","label #"],"associatedMergedColumns":[]},{"number":"40068","isBolded":false,"associatedRows":["token #"],"associatedColumns":["Table 1 : Size of sentences , tokens , and labels for training , validation and test sets .","POS","950011","1699"],"associatedMergedColumns":[]},{"number":"51578","isBolded":false,"associatedRows":["token #","N / A"],"associatedColumns":["Table 1 : Size of sentences , tokens , and labels for training , validation and test sets .","CoNLL2003","204567","3466"],"associatedMergedColumns":[]},{"number":"46666","isBolded":false,"associatedRows":["token #","N / A"],"associatedColumns":["Table 1 : Size of sentences , tokens , and labels for training , validation and test sets .","CoNLL2003","204567","3466","3684"],"associatedMergedColumns":[]},{"number":"14987","isBolded":false,"associatedRows":["training","sentence #","8936"],"associatedColumns":["Table 1 : Size of sentences , tokens , and labels for training , validation and test sets .","CoNLL2003"],"associatedMergedColumns":[]}]},{"caption":"Table 2: Comparison of tagging performance on POS, chunking and NER tasks for various models. \nPOS CoNLL2000 CoNLL2003 \nConv-CRF (Collobert et al., 2011) 96.37 \n90.33 \n81.47 \nLSTM \n97.10 \n92.88 \n79.82 \nBI-LSTM \n97.30 \n93.64 \n81.11 \nRandom CRF \n97.30 \n93.69 \n83.02 \nLSTM-CRF \n97.45 \n93.80 \n84.10 \nBI-LSTM-CRF \n97.43 \n94.13 \n84.26 \nConv-CRF (Collobert et al., 2011) 97.29 \n94.32 \n88.67 (89.59) \nLSTM \n97.29 \n92.99 \n83.74 \nBI-LSTM \n97.40 \n93.92 \n85.17 \nSenna \nCRF \n97.45 \n93.83 \n86.13 \nLSTM-CRF \n97.54 \n94.27 \n88.36 \nBI-LSTM-CRF \n97.55 \n94.46 \n88.83 (90.10) \n\n(0.06) compared to the same model but using \nspelling and context features. \n\n","rows":["LSTM - CRF","LSTM","Random","CRF","BI - LSTM - CRF","Conv - CRF ( Collobert et al . , 2011 )","BI - LSTM","Senna"],"columns":["POS","CoNLL2000","Table 2 : Comparison of tagging performance on POS , chunking and NER tasks for various models .","CoNLL2003"],"mergedAllColumns":[],"numberCells":[{"number":"94.32","isBolded":false,"associatedRows":["Random","Conv - CRF ( Collobert et al . , 2011 )"],"associatedColumns":["Table 2 : Comparison of tagging performance on POS , chunking and NER tasks for various models .","CoNLL2000"],"associatedMergedColumns":[]},{"number":"94.46","isBolded":true,"associatedRows":["Senna","BI - LSTM - CRF"],"associatedColumns":["Table 2 : Comparison of tagging performance on POS , chunking and NER tasks for various models .","CoNLL2000"],"associatedMergedColumns":[]},{"number":"84.10","isBolded":false,"associatedRows":["Random","LSTM - CRF"],"associatedColumns":["Table 2 : Comparison of tagging performance on POS , chunking and NER tasks for various models .","CoNLL2003"],"associatedMergedColumns":[]},{"number":"90.33","isBolded":false,"associatedRows":["Random","Conv - CRF ( Collobert et al . , 2011 )"],"associatedColumns":["Table 2 : Comparison of tagging performance on POS , chunking and NER tasks for various models .","CoNLL2000"],"associatedMergedColumns":[]},{"number":"97.29","isBolded":false,"associatedRows":["Random","Conv - CRF ( Collobert et al . , 2011 )"],"associatedColumns":["Table 2 : Comparison of tagging performance on POS , chunking and NER tasks for various models .","POS"],"associatedMergedColumns":[]},{"number":"97.54","isBolded":false,"associatedRows":["Senna","LSTM - CRF"],"associatedColumns":["Table 2 : Comparison of tagging performance on POS , chunking and NER tasks for various models .","POS"],"associatedMergedColumns":[]},{"number":"94.27","isBolded":false,"associatedRows":["Senna","LSTM - CRF"],"associatedColumns":["Table 2 : Comparison of tagging performance on POS , chunking and NER tasks for various models .","CoNLL2000"],"associatedMergedColumns":[]},{"number":"97.29","isBolded":false,"associatedRows":["Random","LSTM"],"associatedColumns":["Table 2 : Comparison of tagging performance on POS , chunking and NER tasks for various models .","POS"],"associatedMergedColumns":[]},{"number":"83.02","isBolded":false,"associatedRows":["Random","CRF"],"associatedColumns":["Table 2 : Comparison of tagging performance on POS , chunking and NER tasks for various models .","CoNLL2003"],"associatedMergedColumns":[]},{"number":"97.10","isBolded":false,"associatedRows":["Random","LSTM"],"associatedColumns":["Table 2 : Comparison of tagging performance on POS , chunking and NER tasks for various models .","POS"],"associatedMergedColumns":[]},{"number":"97.45","isBolded":true,"associatedRows":["Random","LSTM - CRF"],"associatedColumns":["Table 2 : Comparison of tagging performance on POS , chunking and NER tasks for various models .","POS"],"associatedMergedColumns":[]},{"number":"92.88","isBolded":false,"associatedRows":["Random","LSTM"],"associatedColumns":["Table 2 : Comparison of tagging performance on POS , chunking and NER tasks for various models .","CoNLL2000"],"associatedMergedColumns":[]},{"number":"88.83(90.10)","isBolded":true,"associatedRows":["Senna","BI - LSTM - CRF"],"associatedColumns":["Table 2 : Comparison of tagging performance on POS , chunking and NER tasks for various models .","CoNLL2003"],"associatedMergedColumns":[]},{"number":"97.30","isBolded":false,"associatedRows":["Random","CRF"],"associatedColumns":["Table 2 : Comparison of tagging performance on POS , chunking and NER tasks for various models .","POS"],"associatedMergedColumns":[]},{"number":"93.64","isBolded":false,"associatedRows":["Random","BI - LSTM"],"associatedColumns":["Table 2 : Comparison of tagging performance on POS , chunking and NER tasks for various models .","CoNLL2000"],"associatedMergedColumns":[]},{"number":"93.69","isBolded":false,"associatedRows":["Random","CRF"],"associatedColumns":["Table 2 : Comparison of tagging performance on POS , chunking and NER tasks for various models .","CoNLL2000"],"associatedMergedColumns":[]},{"number":"97.40","isBolded":false,"associatedRows":["Random","BI - LSTM"],"associatedColumns":["Table 2 : Comparison of tagging performance on POS , chunking and NER tasks for various models .","POS"],"associatedMergedColumns":[]},{"number":"83.74","isBolded":false,"associatedRows":["Random","LSTM"],"associatedColumns":["Table 2 : Comparison of tagging performance on POS , chunking and NER tasks for various models .","CoNLL2003"],"associatedMergedColumns":[]},{"number":"86.13","isBolded":false,"associatedRows":["Senna","CRF"],"associatedColumns":["Table 2 : Comparison of tagging performance on POS , chunking and NER tasks for various models .","CoNLL2003"],"associatedMergedColumns":[]},{"number":"92.99","isBolded":false,"associatedRows":["Random","LSTM"],"associatedColumns":["Table 2 : Comparison of tagging performance on POS , chunking and NER tasks for various models .","CoNLL2000"],"associatedMergedColumns":[]},{"number":"97.45","isBolded":false,"associatedRows":["Senna","CRF"],"associatedColumns":["Table 2 : Comparison of tagging performance on POS , chunking and NER tasks for various models .","POS"],"associatedMergedColumns":[]},{"number":"93.83","isBolded":false,"associatedRows":["Senna","CRF"],"associatedColumns":["Table 2 : Comparison of tagging performance on POS , chunking and NER tasks for various models .","CoNLL2000"],"associatedMergedColumns":[]},{"number":"97.43","isBolded":false,"associatedRows":["Random","BI - LSTM - CRF"],"associatedColumns":["Table 2 : Comparison of tagging performance on POS , chunking and NER tasks for various models .","POS"],"associatedMergedColumns":[]},{"number":"97.55","isBolded":true,"associatedRows":["Senna","BI - LSTM - CRF"],"associatedColumns":["Table 2 : Comparison of tagging performance on POS , chunking and NER tasks for various models .","POS"],"associatedMergedColumns":[]},{"number":"96.37","isBolded":false,"associatedRows":["Random","Conv - CRF ( Collobert et al . , 2011 )"],"associatedColumns":["Table 2 : Comparison of tagging performance on POS , chunking and NER tasks for various models .","POS"],"associatedMergedColumns":[]},{"number":"97.30","isBolded":false,"associatedRows":["Random","BI - LSTM"],"associatedColumns":["Table 2 : Comparison of tagging performance on POS , chunking and NER tasks for various models .","POS"],"associatedMergedColumns":[]},{"number":"79.82","isBolded":false,"associatedRows":["Random","LSTM"],"associatedColumns":["Table 2 : Comparison of tagging performance on POS , chunking and NER tasks for various models .","CoNLL2003"],"associatedMergedColumns":[]},{"number":"94.13","isBolded":true,"associatedRows":["Random","BI - LSTM - CRF"],"associatedColumns":["Table 2 : Comparison of tagging performance on POS , chunking and NER tasks for various models .","CoNLL2000"],"associatedMergedColumns":[]},{"number":"88.36","isBolded":false,"associatedRows":["Random","LSTM - CRF"],"associatedColumns":["Table 2 : Comparison of tagging performance on POS , chunking and NER tasks for various models .","CoNLL2003"],"associatedMergedColumns":[]},{"number":"81.11","isBolded":false,"associatedRows":["Random","BI - LSTM"],"associatedColumns":["Table 2 : Comparison of tagging performance on POS , chunking and NER tasks for various models .","CoNLL2003"],"associatedMergedColumns":[]},{"number":"93.80","isBolded":false,"associatedRows":["Random","LSTM - CRF"],"associatedColumns":["Table 2 : Comparison of tagging performance on POS , chunking and NER tasks for various models .","CoNLL2000"],"associatedMergedColumns":[]},{"number":"81.47","isBolded":false,"associatedRows":["Random","Conv - CRF ( Collobert et al . , 2011 )"],"associatedColumns":["Table 2 : Comparison of tagging performance on POS , chunking and NER tasks for various models .","CoNLL2003"],"associatedMergedColumns":[]},{"number":"84.26","isBolded":true,"associatedRows":["Random","BI - LSTM - CRF"],"associatedColumns":["Table 2 : Comparison of tagging performance on POS , chunking and NER tasks for various models .","CoNLL2003"],"associatedMergedColumns":[]},{"number":"88.67(89.59)","isBolded":false,"associatedRows":["Random","Conv - CRF ( Collobert et al . , 2011 )"],"associatedColumns":["Table 2 : Comparison of tagging performance on POS , chunking and NER tasks for various models .","CoNLL2003"],"associatedMergedColumns":[]},{"number":"85.17","isBolded":false,"associatedRows":["Random","BI - LSTM"],"associatedColumns":["Table 2 : Comparison of tagging performance on POS , chunking and NER tasks for various models .","CoNLL2003"],"associatedMergedColumns":[]},{"number":"93.92","isBolded":false,"associatedRows":["Random","BI - LSTM"],"associatedColumns":["Table 2 : Comparison of tagging performance on POS , chunking and NER tasks for various models .","CoNLL2000"],"associatedMergedColumns":[]}]},{"caption":"Table 4: Comparison of tagging accuracy of different models for POS. \nSystem \naccuracy extra data \nMaximum entropy cyclic dependency \n97.24 \nNo \nnetwork (Toutanova et al., 2003) \nSVM-based tagger (Gimenez and Marquez, 2004) \n97.16 \nNo \nBidirectional perceptron learning (Shen et al., 2007) \n97.33 \nNo \nSemi-supervised condensed nearest neighbor \n97.50 \nYes \n(Soegaard, 2011) \nCRFs with structure regularization (Sun, 2014) \n97.36 \nNo \nConv network tagger (Collobert et al., 2011) \n96.37 \nNo \nConv network tagger (senna) (Collobert et al., 2011) \n97.29 \nYes \nBI-LSTM-CRF (ours) \n97.43 \nNo \nBI-LSTM-CRF (Senna) (ours) \n97.55 \nYes \n\n","rows":["Specialized HMM + voting scheme ( Shen and Sarkar , 2005 )","Second order CRF ( Mcdonald et al . , 2005 )","Conv network tagger ( senna ) ( Collobert et al . , 2011 )","BI - LSTM - CRF ( Senna ) ( ours )","SVM classifier ( Kudo and Matsumoto , 2000 )","Second order CRF ( Sha and Pereira , 2003 )","SVM classifier ( Kudo and Matsumoto , 2001 )","Conv - CRF ( Collobert et al . , 2011 )","Second order CRF ( Sun et al . , 2008 )","BI - LSTM - CRF ( ours )"],"columns":["Table 5 : Comparison of F1 scores of different models for chunking .","accuracy"],"mergedAllColumns":[],"numberCells":[{"number":"94.30","isBolded":false,"associatedRows":["Second order CRF ( Sha and Pereira , 2003 )"],"associatedColumns":["Table 5 : Comparison of F1 scores of different models for chunking .","accuracy"],"associatedMergedColumns":[]},{"number":"93.48","isBolded":false,"associatedRows":["SVM classifier ( Kudo and Matsumoto , 2000 )"],"associatedColumns":["Table 5 : Comparison of F1 scores of different models for chunking .","accuracy"],"associatedMergedColumns":[]},{"number":"90.33","isBolded":false,"associatedRows":["Conv - CRF ( Collobert et al . , 2011 )"],"associatedColumns":["Table 5 : Comparison of F1 scores of different models for chunking .","accuracy"],"associatedMergedColumns":[]},{"number":"95.23","isBolded":true,"associatedRows":["Specialized HMM + voting scheme ( Shen and Sarkar , 2005 )"],"associatedColumns":["Table 5 : Comparison of F1 scores of different models for chunking .","accuracy"],"associatedMergedColumns":[]},{"number":"94.29","isBolded":false,"associatedRows":["Second order CRF ( Mcdonald et al . , 2005 )"],"associatedColumns":["Table 5 : Comparison of F1 scores of different models for chunking .","accuracy"],"associatedMergedColumns":[]},{"number":"94.13","isBolded":false,"associatedRows":["BI - LSTM - CRF ( ours )"],"associatedColumns":["Table 5 : Comparison of F1 scores of different models for chunking .","accuracy"],"associatedMergedColumns":[]},{"number":"94.46","isBolded":false,"associatedRows":["BI - LSTM - CRF ( Senna ) ( ours )"],"associatedColumns":["Table 5 : Comparison of F1 scores of different models for chunking .","accuracy"],"associatedMergedColumns":[]},{"number":"93.91","isBolded":false,"associatedRows":["SVM classifier ( Kudo and Matsumoto , 2001 )"],"associatedColumns":["Table 5 : Comparison of F1 scores of different models for chunking .","accuracy"],"associatedMergedColumns":[]},{"number":"94.32","isBolded":false,"associatedRows":["Conv network tagger ( senna ) ( Collobert et al . , 2011 )"],"associatedColumns":["Table 5 : Comparison of F1 scores of different models for chunking .","accuracy"],"associatedMergedColumns":[]},{"number":"94.34","isBolded":false,"associatedRows":["Second order CRF ( Sun et al . , 2008 )"],"associatedColumns":["Table 5 : Comparison of F1 scores of different models for chunking .","accuracy"],"associatedMergedColumns":[]}]},{"caption":"Table 5: Comparison of F1 scores of different models for chunking. \nSystem \naccuracy \nSVM classifier (Kudo and Matsumoto, 2000)  93.48 \nSVM classifier (Kudo and Matsumoto, 2001)  93.91 \nSecond order CRF (Sha and Pereira, 2003)  94.30 \nSpecialized HMM + voting scheme (Shen and Sarkar, 2005)  95.23 \nSecond order CRF (Mcdonald et al., 2005)  94.29 \nSecond order CRF (Sun et al., 2008)  94.34 \nConv-CRF (Collobert et al., 2011)  90.33 \nConv network tagger (senna) (Collobert et al., 2011)  94.32 \nBI-LSTM-CRF (ours) \n94.13 \nBI-LSTM-CRF (Senna) (ours) \n94.46 \n\n","rows":["Specialized HMM + voting scheme ( Shen and Sarkar , 2005 )","Second order CRF ( Mcdonald et al . , 2005 )","Conv network tagger ( senna ) ( Collobert et al . , 2011 )","BI - LSTM - CRF ( Senna ) ( ours )","SVM classifier ( Kudo and Matsumoto , 2000 )","Second order CRF ( Sha and Pereira , 2003 )","SVM classifier ( Kudo and Matsumoto , 2001 )","Conv - CRF ( Collobert et al . , 2011 )","Second order CRF ( Sun et al . , 2008 )","BI - LSTM - CRF ( ours )"],"columns":["Table 5 : Comparison of F1 scores of different models for chunking .","accuracy"],"mergedAllColumns":[],"numberCells":[{"number":"94.13","isBolded":false,"associatedRows":["BI - LSTM - CRF ( ours )"],"associatedColumns":["Table 5 : Comparison of F1 scores of different models for chunking .","accuracy"],"associatedMergedColumns":[]},{"number":"94.34","isBolded":false,"associatedRows":["Second order CRF ( Sun et al . , 2008 )"],"associatedColumns":["Table 5 : Comparison of F1 scores of different models for chunking .","accuracy"],"associatedMergedColumns":[]},{"number":"94.46","isBolded":false,"associatedRows":["BI - LSTM - CRF ( Senna ) ( ours )"],"associatedColumns":["Table 5 : Comparison of F1 scores of different models for chunking .","accuracy"],"associatedMergedColumns":[]},{"number":"94.29","isBolded":false,"associatedRows":["Second order CRF ( Mcdonald et al . , 2005 )"],"associatedColumns":["Table 5 : Comparison of F1 scores of different models for chunking .","accuracy"],"associatedMergedColumns":[]},{"number":"94.32","isBolded":false,"associatedRows":["Conv network tagger ( senna ) ( Collobert et al . , 2011 )"],"associatedColumns":["Table 5 : Comparison of F1 scores of different models for chunking .","accuracy"],"associatedMergedColumns":[]},{"number":"93.91","isBolded":false,"associatedRows":["SVM classifier ( Kudo and Matsumoto , 2001 )"],"associatedColumns":["Table 5 : Comparison of F1 scores of different models for chunking .","accuracy"],"associatedMergedColumns":[]},{"number":"94.30","isBolded":false,"associatedRows":["Second order CRF ( Sha and Pereira , 2003 )"],"associatedColumns":["Table 5 : Comparison of F1 scores of different models for chunking .","accuracy"],"associatedMergedColumns":[]},{"number":"95.23","isBolded":true,"associatedRows":["Specialized HMM + voting scheme ( Shen and Sarkar , 2005 )"],"associatedColumns":["Table 5 : Comparison of F1 scores of different models for chunking .","accuracy"],"associatedMergedColumns":[]},{"number":"93.48","isBolded":false,"associatedRows":["SVM classifier ( Kudo and Matsumoto , 2000 )"],"associatedColumns":["Table 5 : Comparison of F1 scores of different models for chunking .","accuracy"],"associatedMergedColumns":[]},{"number":"90.33","isBolded":false,"associatedRows":["Conv - CRF ( Collobert et al . , 2011 )"],"associatedColumns":["Table 5 : Comparison of F1 scores of different models for chunking .","accuracy"],"associatedMergedColumns":[]}]}]